setup.py
candidator/__init__.py
candidator/manage.py
candidator/settings.py
candidator/urls.py
candidator/elections/__init__.py
candidator/elections/admin.py
candidator/elections/api.py
candidator/elections/api_urls.py
candidator/elections/api_v2.py
candidator/elections/exceptions.py
candidator/elections/models.py
candidator/elections/urls.py
candidator/elections/forms/__init__.py
candidator/elections/forms/candidate_form.py
candidator/elections/forms/election_form.py
candidator/elections/management/__init__.py
candidator/elections/management/commands/__init__.py
candidator/elections/management/commands/elections_destroyer.py
candidator/elections/management/commands/elections_loader.py
candidator/elections/templatetags/__init__.py
candidator/elections/templatetags/candidate_tags.py
candidator/elections/templatetags/election_tags.py
candidator/elections/templatetags/settingsvars_tags.py
candidator/elections/tests/__init__.py
candidator/elections/tests/answer.py
candidator/elections/tests/api.py
candidator/elections/tests/api_v2.py
candidator/elections/tests/background.py
candidator/elections/tests/background_category.py
candidator/elections/tests/candidate.py
candidator/elections/tests/candidate_answer.py
candidator/elections/tests/category.py
candidator/elections/tests/election.py
candidator/elections/tests/election_embeded.py
candidator/elections/tests/election_loader.py
candidator/elections/tests/information_source.py
candidator/elections/tests/link.py
candidator/elections/tests/medianaranja.py
candidator/elections/tests/personal_data.py
candidator/elections/tests/question.py
candidator/elections/tests/report.py
candidator/elections/tests/settings_variables.py
candidator/elections/tests/user.py
candidator/elections/views/__init__.py
candidator/elections/views/answer_views.py
candidator/elections/views/background_category_views.py
candidator/elections/views/background_views.py
candidator/elections/views/candidate_views.py
candideitorg_django.egg-info/PKG-INFO
candideitorg_django.egg-info/SOURCES.txt
candideitorg_django.egg-info/dependency_links.txt
candideitorg_django.egg-info/requires.txt
candideitorg_django.egg-info/top_level.txt