Metadata-Version: 1.1
Name: candideitorg-django
Version: 0.0.1
Summary: UNKNOWN
Home-page: https://github.com/ciudadanointeligente/candideitorg-django
Author: Fundación Ciudadano Inteligente
Author-email: lab@ciudadanointeligente.org
License: GNU Affero General Public License v3
Platform: UNKNOWN
Classifier: Development Status :: 3 - Alpha
Classifier: Environment :: Web Environment
Classifier: Framework :: Django
Classifier: Intended Audience :: Developers
Classifier: License :: OSI Approved :: GNU Affero General Public License v3
Classifier: Operating System :: OS Independent
Classifier: Programming Language :: Python
